{
    "ines": {
        "username": "ines",
        "email": "ines@mail.com",
        "password": "pass123",
        "name": "In\u00e9s",
        "age": 20,
        "country": "Andorra"
    },
    "alex": {
        "username": "alex",
        "email": "alex@mail.com",
        "password": "pass321",
        "name": "Alex",
        "age": 19,
        "country": "Miami"
    },
    "maria": {
        "username": "maria",
        "email": "maria@hotmail.com",
        "password": "pass231",
        "name": "Mar\u00eda",
        "age": 21,
        "country": "Spain"
    }
}